<?xml version="1.0" encoding="UTF-8"?>
<?xml-model href="https://music-encoding.org/schema/dev/mei-Mensural.rng" type="application/xml" schematypens="http://relaxng.org/ns/structure/1.0"?>
<?xml-model href="https://music-encoding.org/schema/dev/mei-Mensural.rng" type="application/xml" schematypens="http://purl.oclc.org/dsdl/schematron"?>
<mei
    xmlns="http://www.music-encoding.org/ns/mei" meiversion="5.0.0-dev"
    xmlns:xlink="http://www.w3.org/1999/xlink">
    <meiHead>
        <fileDesc>
            <titleStmt>
                <title>06 Missa sobre las voces - Sanctus (Section 3)</title>
                <composer>Cristóbal de Morales</composer>
                <funder>
                    <corpName>Brandeis University</corpName>
                </funder>
                <funder>
                    <corpName>National Endowment for the Humanities (NEH)</corpName>
                </funder>
                <respStmt>
                    <persName role="project director" auth="VIAF" auth.uri="http://viaf.org/viaf/" codedval="316001213">Karen Desmond</persName>
                    <persName role="encoder">MuRET</persName>
                    <persName role="encoder">Martha Eladia Thomae Elias</persName>
                    <persName role="editor">Martha Eladia Thomae Elias</persName>
                </respStmt>
            </titleStmt>
            <pubStmt>
                <publisher>
                    <persName>Karen Desmond</persName>
                    <corpName>Brandeis University</corpName>
                </publisher>
                <date>2022</date>
                <availability>
                    <useRestrict>Available for purposes of academic research and teaching only.</useRestrict>
                </availability>
            </pubStmt>
            <seriesStmt>
                <title>Measuring Polyphony: Digital Encodings of Late Medieval Music</title>
                <editor>
                    <persName>Karen Desmond</persName>
                </editor>
                <identifier>
                    <ref targettype="home_page" target="http://www.measuringpolyphony.org/"/>
                </identifier>
            </seriesStmt>
            <notesStmt>
                <annot label="original_clefs"/>
                <annot label="commentary"/>
            </notesStmt>
            <sourceDesc>
                <source targettype="IIIF" target="https://muret.dlsi.ua.es/iiif/6/213/manifest.json">
                    <locus>29v.jpg</locus>
                </source>
            </sourceDesc>
        </fileDesc>
        <encodingDesc>
            <appInfo>
                <application xml:id="MPEditor">
                    <name>Measuring Polyphony Editor</name>
                </application>
            </appInfo>
            <editorialDecl>
                <p>This MEI encoding in mensural notation was made using the Measuring Polyphony Editor, transcribed from IIIF images of the original manuscript source one staff at a time, entering the pitches and rhythms for each stave using a combination of number and letter keystrokes. The Measuring Polyphony Editor generates two MEI files from this user input: an MEI parts file that captures each voice part entered, and an MEI score file that scores up the voice parts, which is viewable here.</p>
            </editorialDecl>
            <projectDesc>
                <p>The Measuring Polyphony Editor, funded by a 2019-2020 NEH Digital Humanities Grant, is a prototype tool that allows a variety of modern readers (students and experts, musicologists, music theorists, those interested in the history of music notation, counterpoint, medieval palaeography and/or manuscript studies) to access and contribute transcriptions of music directly linked to digital images of the medieval manuscripts, and to learn about the original notation. This tool will offer new possibilities for the analysis and interpretation of late medieval music. In a broader humanities context, the project investigates how modeling the meanings of notational signs can lead to new understandings of the interaction between the sign and the signified, and of the relationship between notational style and changes in musical style across time and place.</p>
            </projectDesc>
        </encodingDesc>
        <workList>
            <work>
                <identifier type="catalogue_number"/>
                <title>06 Missa sobre las voces - Sanctus (Section 3)</title>
                <composer>Cristóbal de Morales</composer>
                <incip>
                    <incipText label="superius" corresp="#superius">
                        <lg>
                            <l>[SUPERIUS]</l>
                        </lg>
                    </incipText>
                    <incipText label="altus" corresp="#altus">
                        <lg>
                            <l>[ALTUS]</l>
                        </lg>
                    </incipText>
                    <incipText label="tenor" corresp="#tenor">
                        <lg>
                            <l>[TENOR]</l>
                        </lg>
                    </incipText>
                </incip>
                <classification>
                    <termList>
                        <term>Mass Movement</term>
                    </termList>
                </classification>
            </work>
        </workList>
        <manifestationList>
            <manifestation singleton="true">
                <titleStmt>
                    <title>
                        <identifier label="siglum">GuatC 1</identifier>
                    </title>
                </titleStmt>
                <physLoc>
                    <repository>
                        <corpName>[LIBRARY NAME]</corpName>
                        <identifier>[SHELFMARK]</identifier>
                        <ptr targettype="IIIF" target="https://muret.dlsi.ua.es/iiif/6/213/manifest.json"/>
                    </repository>
                </physLoc>
                <notesStmt>
                    <annot>Primary manuscript source for this encoding.</annot>
                </notesStmt>
            </manifestation>
        </manifestationList>
    </meiHead>
    <music>
        <facsimile>
            <surface xml:id="m-6f75cebc-cb5e-4ac9-87ba-fadd476b87c7">
                <graphic xml:id="m-7fcc2214-f1ab-4d09-a7ad-fa3727f972b4" target="https://muret.dlsi.ua.es/iiif/6:213/canvas/f25">
                    <zone xml:id="mb1b1432a-54d5-4ff1-8a59-8e708063a1d2" ulx="283" uly="108" lrx="1119" lry="283"/>
                    <zone xml:id="mbcfe3007-5178-4b8b-ac68-af2b722e5448" ulx="142" uly="298" lrx="1109" lry="439"/>
                    <zone xml:id="m548c4d0a-9651-4b67-a27f-f819015db201" ulx="143" uly="467" lrx="1121" lry="602"/>
                    <zone xml:id="m4810a235-b2c1-4c1b-9f57-4efa13d83b6e" ulx="132" uly="622" lrx="1094" lry="764"/>
                    <zone xml:id="mc2d5b6d1-3b39-412a-8d04-3dc2e7fc2df5" ulx="280" uly="900" lrx="1112" lry="1037"/>
                    <zone xml:id="m9728e447-40e2-4581-b928-a9be8c248b79" ulx="154" uly="1062" lrx="1127" lry="1196"/>
                    <zone xml:id="md4ec16b7-5918-4d6d-882c-f8f00be4a3fd" ulx="145" uly="1217" lrx="1113" lry="1350"/>
                    <zone xml:id="m7b1cb535-5a11-4300-b8f2-2ec0e2deebc1" ulx="144" uly="1374" lrx="1095" lry="1503"/>
                </graphic>
            </surface>
            <surface xml:id="m-0803a703-4308-4988-8d7a-533ce1c3183c">
                <graphic xml:id="m-6e1d3f21-e40d-4e03-8032-554c34a687d7" target="https://muret.dlsi.ua.es/iiif/6:213/canvas/f26">
                    <zone xml:id="m91def5cb-ef51-4ee7-92e8-9f6e387fa442" ulx="317" uly="115" lrx="1148" lry="267"/>
                    <zone xml:id="m41cccbdf-1a42-4571-a1f2-137bd938a404" ulx="183" uly="286" lrx="1147" lry="438"/>
                    <zone xml:id="m27eb63a3-ac17-4c21-9ddd-2c61ac3369c4" ulx="179" uly="470" lrx="1119" lry="609"/>
                </graphic>
            </surface>
        </facsimile>
        <body>
            <mdiv>
                <score>
                    <scoreDef midi.bpm="600">
                        <staffGrp symbol="bracket">
                            <staffDef n="1" lines="5" notationtype="mensural.white" xml:id="superius" clef.shape="G" clef.line="2">
                                <label>superius</label>
                                <mensur modusminor="2" tempus="2" prolatio="2" sign="C"/>
                            </staffDef>
                            <staffDef n="2" lines="5" notationtype="mensural.white" xml:id="altus" clef.shape="C" clef.line="2">
                                <label>altus</label>
                                <mensur modusminor="2" tempus="2" prolatio="2" sign="C"/>
                            </staffDef>
                            <staffDef n="3" lines="5" notationtype="mensural.white" xml:id="tenor" clef.shape="C" clef.line="3">
                                <label>tenor</label>
                                <mensur modusminor="2" tempus="2" prolatio="2" sign="C"/>
                            </staffDef>
                        </staffGrp>
                    </scoreDef>
                    <section>
                        <staff n="1">
                            <layer n="1">
                                <rest xml:id="PART467cc2a5-5027-4e70-899a-30eaadab7dda_A0a327798-6e12-4a53-8205-21aa967ab72c" dur="longa"/>
                                <barLine form="dashed"/>
                                <note xml:id="PART467cc2a5-5027-4e70-899a-30eaadab7dda_A3f752d6f-c3b4-4a5f-b80a-4c0a0f47ba54" dur="semibrevis" oct="4" pname="g">
                                    <verse xml:id="m-d854c4e8-d518-46a9-96fb-3865d35e6c82" color="black" n="1">
                                        <syl xml:id="m-6a990f7f-bec6-4744-b525-5f56f62adcd7" con="b">29v.jpg,</syl>
                                        <syl xml:id="m-a4df06c2-13fa-4d63-a9a4-442afa5fa7cc" con="b">p1,</syl>
                                        <syl xml:id="m-c39d4b1e-2a0c-455b-8552-0ba7353dc154">s1</syl>
                                    </verse>
                                </note>
                                <note xml:id="PART467cc2a5-5027-4e70-899a-30eaadab7dda_A4142777a-8d1d-4226-a0df-5aff2e09008b" dur="minima" oct="4" pname="g"/>
                                <note xml:id="PART467cc2a5-5027-4e70-899a-30eaadab7dda_A0ee855c2-6e01-495c-9993-188d552769ab" dur="minima" oct="4" pname="a"/>
                                <barLine form="dashed"/>
                                <note xml:id="PART467cc2a5-5027-4e70-899a-30eaadab7dda_A7dc1d816-81a6-446e-9f52-88b6c0e0990d" dur="minima" oct="4" pname="b"/>
                                <note xml:id="PART467cc2a5-5027-4e70-899a-30eaadab7dda_Addd05b63-0e1c-48b5-b882-b8ec8dad1236" dur="minima" oct="5" pname="c"/>
                                <note xml:id="PART467cc2a5-5027-4e70-899a-30eaadab7dda_A5499df3b-29d1-4a0f-827e-100fe607ddb2" dur="semibrevis" oct="5" pname="d"/>
                                <barLine form="dashed"/>
                                <note xml:id="PART467cc2a5-5027-4e70-899a-30eaadab7dda_A73d57091-fa93-44b6-a4e2-d521352ceabd" dur="minima" oct="5" pname="e"/>
                                <note xml:id="PART467cc2a5-5027-4e70-899a-30eaadab7dda_Acb0de2bb-c594-4055-b596-7c98f797aca4" dur="semibrevis" oct="5" pname="g"/>
                                <note xml:id="PART467cc2a5-5027-4e70-899a-30eaadab7dda_A7b0f6479-666c-427a-8157-70c65f40baf7" dur="minima" oct="5" pname="f"/>
                                <barLine form="dashed"/>
                                <note xml:id="PART467cc2a5-5027-4e70-899a-30eaadab7dda_A7b95e7fe-b7d2-4433-9cbb-e8ecd086a744" dur="minima" oct="5" pname="e"/>
                                <note xml:id="PART467cc2a5-5027-4e70-899a-30eaadab7dda_A4fdf20ef-d0b6-4369-a3b4-7d2c786aa6ba" dur="semibrevis" oct="5" pname="d"/>
                                <note xml:id="PART467cc2a5-5027-4e70-899a-30eaadab7dda_Aedf3f24d-52d0-40cd-aaab-dd2924667e83" dur="semiminima" oct="5" pname="c"/>
                                <note xml:id="PART467cc2a5-5027-4e70-899a-30eaadab7dda_Af092b5fe-94bd-4273-9572-172425aaf596" dur="semiminima" oct="4" pname="b"/>
                                <barLine form="dashed"/>
                                <note xml:id="PART467cc2a5-5027-4e70-899a-30eaadab7dda_A4b2a11b8-6d0f-40e2-b83c-372e97e29a22" dur="minima" oct="5" pname="c"/>
                                <note xml:id="PART467cc2a5-5027-4e70-899a-30eaadab7dda_Ad068f697-87e7-4412-9742-76c7b470eace" dur="minima" oct="5" pname="e">
                                    <verse xml:id="m-815b8bce-b9ca-4948-9bc6-59f7e2abd555" color="black" n="1">
                                        <syl xml:id="m-5f8b63c5-3306-4aff-9c6e-c93f896efb93" con="b">29v.jpg,</syl>
                                        <syl xml:id="m-71e55841-6fb1-4b66-8a10-6b395ed7126c" con="b">p1,</syl>
                                        <syl xml:id="m-edb76b9c-cfc5-41b1-bdc5-ae67e78d5e21">s2</syl>
                                    </verse>
                                </note>
                                <note xml:id="PART467cc2a5-5027-4e70-899a-30eaadab7dda_A442e3d57-481f-41c8-af09-05bc2a4de997" dur="minima" oct="5" pname="e"/>
                                <note xml:id="PART467cc2a5-5027-4e70-899a-30eaadab7dda_A5f356a83-61f1-45d0-ae4d-b21dcadc5693" dur="minima" oct="5" pname="e"/>
                                <barLine form="dashed"/>
                                <note xml:id="PART467cc2a5-5027-4e70-899a-30eaadab7dda_Aec79583f-0ea8-4e82-a554-04bd676de2c2" dur="minima" oct="4" pname="a"/>
                                <note xml:id="PART467cc2a5-5027-4e70-899a-30eaadab7dda_A83850117-fa1e-44f2-aed8-a6168f73e4d1" dur="semibrevis" oct="5" pname="e"/>
                                <note xml:id="PART467cc2a5-5027-4e70-899a-30eaadab7dda_A60f32806-1362-4879-9389-a683a7322507" dur="minima" oct="5" pname="d"/>
                                <barLine form="dashed"/>
                                <note xml:id="PART467cc2a5-5027-4e70-899a-30eaadab7dda_Aef04fd64-1979-46d6-9063-ddb60a141632" dur="minima" oct="5" pname="c"/>
                                <note xml:id="PART467cc2a5-5027-4e70-899a-30eaadab7dda_A286b7410-21c7-4541-93de-730e8865d8b7" dur="semiminima" oct="4" pname="b"/>
                                <note xml:id="PART467cc2a5-5027-4e70-899a-30eaadab7dda_Ae39d8fe7-922a-4206-bab7-df4e9d5d6cc7" dur="semiminima" oct="4" pname="a"/>
                                <note xml:id="PART467cc2a5-5027-4e70-899a-30eaadab7dda_A8cd8bd1b-4c9f-49b1-a9be-e25e14e5c87c" dur="minima" oct="4" pname="b"/>
                                <note xml:id="PART467cc2a5-5027-4e70-899a-30eaadab7dda_A5027b6b4-ba70-4ea1-85aa-776734dee822" dur="minima" oct="5" pname="e"/>
                                <barLine form="dashed"/>
                                <note xml:id="PART467cc2a5-5027-4e70-899a-30eaadab7dda_A69b77452-ebe8-46c7-ba16-6144763bc191" dur="minima" oct="5" pname="e"/>
                                <note xml:id="PART467cc2a5-5027-4e70-899a-30eaadab7dda_Aa08d0764-5208-4da1-84ba-90eecca3b7fc" dur="minima" oct="5" pname="d"/>
                                <note xml:id="PART467cc2a5-5027-4e70-899a-30eaadab7dda_A9a72e1c6-9886-4156-82e3-fef68a57b0a4" dur="minima" oct="5" pname="f"/>
                                <note xml:id="PART467cc2a5-5027-4e70-899a-30eaadab7dda_Ac64dc3e5-5758-4719-88da-2b4e08410925" dur="semibrevis" oct="5" pname="e"/>
                                <note xml:id="PART467cc2a5-5027-4e70-899a-30eaadab7dda_Ac329412d-14ea-485a-a5c3-e5df102edc7d" dur="semiminima" oct="5" pname="d"/>
                                <note xml:id="PART467cc2a5-5027-4e70-899a-30eaadab7dda_A1429fe88-9802-4457-b290-d8d79a035e1d" dur="semiminima" oct="5" pname="c"/>
                                <note xml:id="PART467cc2a5-5027-4e70-899a-30eaadab7dda_Afd6bff5f-c3fd-40e4-9e2e-42c6de848d17" dur="minima" oct="4" pname="b"/>
                                <note xml:id="PART467cc2a5-5027-4e70-899a-30eaadab7dda_Aed570359-df18-4383-8202-5736043b1f45" dur="semiminima" oct="4" pname="a"/>
                                <note xml:id="PART467cc2a5-5027-4e70-899a-30eaadab7dda_Af35f01d5-2ddf-4795-880c-d97f05af3fb4" dur="semiminima" oct="4" pname="b"/>
                                <barLine form="dashed"/>
                                <note xml:id="PART467cc2a5-5027-4e70-899a-30eaadab7dda_A7ac5c28a-fe6d-4bc6-b404-43bc152d38eb" dur="semiminima" oct="5" pname="c">
                                    <verse xml:id="m-d4c00d74-e64f-4c75-bddd-b62403f6615a" color="black" n="1">
                                        <syl xml:id="m-77d2aa2c-7664-4f8b-8655-a30f006e8f17" con="b">29v.jpg,</syl>
                                        <syl xml:id="m-a1da6e4b-5189-46ae-984c-f61532ea3f44" con="b">p1,</syl>
                                        <syl xml:id="m-64aec5c3-69a2-4d90-8e97-c076c3495c89">s3</syl>
                                    </verse>
                                </note>
                                <note xml:id="PART467cc2a5-5027-4e70-899a-30eaadab7dda_A9558f897-ce48-43bc-9e30-696da648e803" dur="semiminima" oct="5" pname="d"/>
                                <note xml:id="PART467cc2a5-5027-4e70-899a-30eaadab7dda_A37976072-686b-4d40-8b2a-c52792bc99c0" dur="semibrevis" oct="5" pname="e"/>
                                <note xml:id="PART467cc2a5-5027-4e70-899a-30eaadab7dda_Acd2e44b1-d4b1-412e-9aa0-fcfc6090b39a" dur="minima" oct="5" pname="d"/>
                                <barLine form="dashed"/>
                                <note xml:id="PART467cc2a5-5027-4e70-899a-30eaadab7dda_Aacc459b2-b788-4ee5-ba91-b43dd5799941" dur="minima" oct="5" pname="e" dur.quality="perfecta" num="2" numbase="3"/>
                                <dot xml:id="m-5259b3a3-fc1d-4506-b3e8-2cc936423412" form="aug"/>
                                <note xml:id="PART467cc2a5-5027-4e70-899a-30eaadab7dda_Af17a69e3-a663-4b9c-8c8e-c56d9ecc0dd3" dur="semiminima" oct="5" pname="d"/>
                                <note xml:id="PART467cc2a5-5027-4e70-899a-30eaadab7dda_A2ce321b2-9801-4caf-b97c-a68a915d142d" dur="minima" oct="5" pname="c"/>
                                <note xml:id="PART467cc2a5-5027-4e70-899a-30eaadab7dda_A150d8d7c-b13e-4ee6-ad3c-7217eb74cee2" dur="minima" oct="4" pname="b"/>
                                <barLine form="dashed"/>
                                <note xml:id="PART467cc2a5-5027-4e70-899a-30eaadab7dda_A6774a814-ada0-4504-9d0c-d2ebd03c8cbb" dur="minima" oct="4" pname="a"/>
                                <note xml:id="PART467cc2a5-5027-4e70-899a-30eaadab7dda_A4598b173-588b-417a-b7f5-27a4e7f91c5f" dur="semiminima" oct="4" pname="g"/>
                                <note xml:id="PART467cc2a5-5027-4e70-899a-30eaadab7dda_Ac2161b31-1ee3-4d17-b567-6759af291259" dur="semiminima" oct="4" pname="f"/>
                                <note xml:id="PART467cc2a5-5027-4e70-899a-30eaadab7dda_A735df1d3-2e75-4634-a041-d6d3a58aedca" dur="semibrevis" oct="4" pname="g"/>
                                <barLine form="dashed"/>
                                <rest xml:id="PART467cc2a5-5027-4e70-899a-30eaadab7dda_Afad45b86-5373-449a-bd02-a1068c77bb45" dur="minima"/>
                                <note xml:id="PART467cc2a5-5027-4e70-899a-30eaadab7dda_Accf7bc02-9dd0-4f86-9e38-c39392b14dad" dur="minima" oct="4" pname="a"/>
                                <note xml:id="PART467cc2a5-5027-4e70-899a-30eaadab7dda_A02b6124a-2824-40b1-b174-6c00c03c1501" dur="minima" oct="4" pname="a"/>
                                <note xml:id="PART467cc2a5-5027-4e70-899a-30eaadab7dda_Aa0812aef-6a80-4806-96bf-9db8d125fa59" dur="minima" oct="4" pname="g"/>
                                <barLine form="dashed"/>
                                <note xml:id="PART467cc2a5-5027-4e70-899a-30eaadab7dda_A6d29b04c-7029-4c4a-b4df-d2ea6d550422" dur="minima" oct="4" pname="a"/>
                                <note xml:id="PART467cc2a5-5027-4e70-899a-30eaadab7dda_A54875de9-e87a-408d-b2df-aaff0e065b2a" dur="semibrevis" oct="5" pname="c"/>
                                <note xml:id="PART467cc2a5-5027-4e70-899a-30eaadab7dda_A23ba6b02-1d10-4a55-97b9-d6c312c88258" dur="minima" oct="4" pname="b"/>
                                <barLine form="dashed"/>
                                <note xml:id="PART467cc2a5-5027-4e70-899a-30eaadab7dda_Aa499ba2d-76bd-4df7-bb09-b60d20a6f858" dur="semiminima" oct="5" pname="c"/>
                                <note xml:id="PART467cc2a5-5027-4e70-899a-30eaadab7dda_A60839670-f87c-49bd-abce-53f695ab402c" dur="semiminima" oct="4" pname="b"/>
                                <note xml:id="PART467cc2a5-5027-4e70-899a-30eaadab7dda_A1a8dadde-362a-4de9-85a9-66fdee196c17" dur="semiminima" oct="4" pname="a">
                                    <verse xml:id="m-9ff39c81-3630-45ad-bb81-545625ae084c" color="black" n="1">
                                        <syl xml:id="m-81576b1b-f824-4def-99a3-23347ffc26e8" con="b">29v.jpg,</syl>
                                        <syl xml:id="m-c8dd022b-cf5c-4d1f-bb25-279d563cf023" con="b">p1,</syl>
                                        <syl xml:id="m-380d6c6c-d635-4353-9bf3-d9258b0a8880">s4</syl>
                                    </verse>
                                </note>
                                <note xml:id="PART467cc2a5-5027-4e70-899a-30eaadab7dda_A6393e8af-e62b-4087-8278-c67d6b35ee84" dur="semiminima" oct="4" pname="g"/>
                                <note xml:id="PART467cc2a5-5027-4e70-899a-30eaadab7dda_Abbd5737e-4da1-45cf-ba6f-289943eea3d3" dur="semibrevis" oct="4" pname="a"/>
                                <barLine form="dashed"/>
                                <rest xml:id="PART467cc2a5-5027-4e70-899a-30eaadab7dda_A5e4f6700-dc49-4ca1-9264-247c6e83687a" dur="minima"/>
                                <note xml:id="PART467cc2a5-5027-4e70-899a-30eaadab7dda_A64b9fa06-2d04-497b-aeba-e3c11976dd63" dur="minima" oct="5" pname="d"/>
                                <note xml:id="PART467cc2a5-5027-4e70-899a-30eaadab7dda_A947a6897-eaa8-4b79-b088-17ccb2e14924" dur="minima" oct="5" pname="d"/>
                                <note xml:id="PART467cc2a5-5027-4e70-899a-30eaadab7dda_A7859d8ce-02ac-4cee-89a1-9cfd6161a5f4" dur="minima" oct="5" pname="c"/>
                                <barLine form="dashed"/>
                                <note xml:id="PART467cc2a5-5027-4e70-899a-30eaadab7dda_Aa9e9a7ee-7e4b-439f-be14-86ab1056bd6b" dur="minima" oct="5" pname="d"/>
                                <note xml:id="PART467cc2a5-5027-4e70-899a-30eaadab7dda_A517aa2d9-00b7-428f-b357-b2a5a6b54ecc" dur="semibrevis" oct="5" pname="f"/>
                                <note xml:id="PART467cc2a5-5027-4e70-899a-30eaadab7dda_A91bf4a6d-f882-4c89-b147-98a7e951d0b1" dur="minima" oct="5" pname="e"/>
                                <barLine form="dashed"/>
                                <note xml:id="PART467cc2a5-5027-4e70-899a-30eaadab7dda_A92599e4f-d343-406e-8713-c679ef14c70d" dur="semiminima" oct="5" pname="f"/>
                                <note xml:id="PART467cc2a5-5027-4e70-899a-30eaadab7dda_Acf89f0eb-b903-4caa-97e5-e74dd7dab2d0" dur="semiminima" oct="5" pname="e"/>
                                <note xml:id="PART467cc2a5-5027-4e70-899a-30eaadab7dda_Aa6ce687a-2b07-41f4-82f8-c036e449a6f7" dur="semiminima" oct="5" pname="d"/>
                                <note xml:id="PART467cc2a5-5027-4e70-899a-30eaadab7dda_Ab1ed7ed3-065d-43a2-941b-1ea768e01644" dur="semiminima" oct="5" pname="c"/>
                                <note xml:id="PART467cc2a5-5027-4e70-899a-30eaadab7dda_A1c26f3ad-50b7-4fff-a615-88409a7c407d" dur="semibrevis" oct="5" pname="d" dur.quality="perfecta" num="2" numbase="3"/>
                                <dot xml:id="m-d666a92d-1e79-4cbb-a77f-0086bccc61bb" form="aug"/>
                                <note xml:id="PART467cc2a5-5027-4e70-899a-30eaadab7dda_Ae72d3ebc-f1b3-4165-a6e5-1589044e8184" dur="semiminima" oct="5" pname="c"/>
                                <note xml:id="PART467cc2a5-5027-4e70-899a-30eaadab7dda_Aac3b083e-09af-4ec6-a533-f1b26d25c831" dur="semiminima" oct="4" pname="b"/>
                                <note xml:id="PART467cc2a5-5027-4e70-899a-30eaadab7dda_A9d3b4e67-f791-4224-b3e4-ede3694844ee" dur="semibrevis" oct="5" pname="c"/>
                                <barLine form="dashed"/>
                            </layer>
                        </staff>
                        <staff n="2">
                            <layer n="1">
                                <rest xml:id="PART05f0e239-2c20-45c2-9e2f-7d2db6cd46ef_A915008ba-2b89-4a36-aa59-911587f864ff" dur="longa"/>
                                <barLine form="dashed"/>
                                <rest xml:id="PART05f0e239-2c20-45c2-9e2f-7d2db6cd46ef_A802d3d6b-694e-4f87-91b5-0373ce9d21f9" dur="longa"/>
                                <barLine form="dashed"/>
                                <note xml:id="PART05f0e239-2c20-45c2-9e2f-7d2db6cd46ef_A4f0e980b-c007-413e-85ec-56a7b42c819f" dur="semibrevis" oct="4" pname="c">
                                    <verse xml:id="m-0ca38642-112a-47c7-9689-bc831bb5d9c3" color="black" n="1">
                                        <syl xml:id="m-2534879e-7b8d-4d83-815f-177821b4f179" con="b">30r.jpg,</syl>
                                        <syl xml:id="m-261811f3-ab86-4905-81d6-7eddd5555993" con="b">p1,</syl>
                                        <syl xml:id="m-abece8ea-1e31-4e08-a5c2-6ed8d4a128d1">s1</syl>
                                    </verse>
                                </note>
                                <note xml:id="PART05f0e239-2c20-45c2-9e2f-7d2db6cd46ef_A7600c593-9824-4a5c-8797-0e548922503b" dur="minima" oct="4" pname="c"/>
                                <note xml:id="PART05f0e239-2c20-45c2-9e2f-7d2db6cd46ef_Aabcb974f-28b6-4ba1-994b-20c8ebaaafb8" dur="minima" oct="4" pname="d"/>
                                <barLine form="dashed"/>
                                <note xml:id="PART05f0e239-2c20-45c2-9e2f-7d2db6cd46ef_A6523ede5-1284-4f26-826b-cd9f01ad899c" dur="minima" oct="4" pname="e"/>
                                <note xml:id="PART05f0e239-2c20-45c2-9e2f-7d2db6cd46ef_A6df470c6-0c8e-4551-96bc-8546b5f9be1f" dur="minima" oct="4" pname="f"/>
                                <note xml:id="PART05f0e239-2c20-45c2-9e2f-7d2db6cd46ef_A0c4ea89b-c0eb-4100-9183-f6f0d7ea5028" dur="semibrevis" oct="4" pname="g"/>
                                <barLine form="dashed"/>
                                <note xml:id="PART05f0e239-2c20-45c2-9e2f-7d2db6cd46ef_A7eeea2f6-6484-4057-842a-ecf5e3b577a7" dur="brevis" oct="4" pname="a"/>
                                <barLine form="dashed"/>
                                <rest xml:id="PART05f0e239-2c20-45c2-9e2f-7d2db6cd46ef_Aa9328618-24c6-47fa-b221-cf489b5123eb" dur="minima"/>
                                <note xml:id="PART05f0e239-2c20-45c2-9e2f-7d2db6cd46ef_Abed07f81-717f-4efc-b689-0cdf556a8756" dur="minima" oct="4" pname="c"/>
                                <note xml:id="PART05f0e239-2c20-45c2-9e2f-7d2db6cd46ef_A5bffdbcf-57e6-469b-bfac-d221c4988d74" dur="minima" oct="4" pname="c"/>
                                <note xml:id="PART05f0e239-2c20-45c2-9e2f-7d2db6cd46ef_A8234bb50-d854-4005-9d05-b9914aa900af" dur="minima" oct="4" pname="d"/>
                                <barLine form="dashed"/>
                                <note xml:id="PART05f0e239-2c20-45c2-9e2f-7d2db6cd46ef_Acffbf724-1636-48d1-bb31-9ea0c909b79a" dur="minima" oct="4" pname="e" dur.quality="perfecta" num="2" numbase="3"/>
                                <dot xml:id="m-936b8906-7500-4142-91fc-01f79ef56faf" form="aug"/>
                                <note xml:id="PART05f0e239-2c20-45c2-9e2f-7d2db6cd46ef_A74d9dc75-f3a3-46a4-9de4-2e0ff8942ce1" dur="semiminima" oct="4" pname="f"/>
                                <note xml:id="PART05f0e239-2c20-45c2-9e2f-7d2db6cd46ef_A10ee1cc1-4bb7-4a24-a484-164f03efdc05" dur="semibrevis" oct="4" pname="g"/>
                                <barLine form="dashed"/>
                                <note xml:id="PART05f0e239-2c20-45c2-9e2f-7d2db6cd46ef_A1379e816-6eca-4559-9b89-1dcc364099d8" dur="semibrevis" oct="4" pname="a"/>
                                <rest xml:id="PART05f0e239-2c20-45c2-9e2f-7d2db6cd46ef_Af053191b-b881-43df-9c7b-cc0ffec19d33" dur="minima"/>
                                <note xml:id="PART05f0e239-2c20-45c2-9e2f-7d2db6cd46ef_A143edad4-b3ff-4fdc-a12e-4915ca57f93e" dur="minima" oct="4" pname="a">
                                    <verse xml:id="m-25d0eff8-daa7-4965-9579-492fce4046f0" color="black" n="1">
                                        <syl xml:id="m-d4870c62-6caa-4762-a8eb-9c34028f2715" con="b">30r.jpg,</syl>
                                        <syl xml:id="m-1668408b-ea2a-4b2a-a653-332f960f2f2b" con="b">p1,</syl>
                                        <syl xml:id="m-0ac96f22-6aef-4654-82fd-478209f89da3">s2</syl>
                                    </verse>
                                </note>
                                <barLine form="dashed"/>
                                <note xml:id="PART05f0e239-2c20-45c2-9e2f-7d2db6cd46ef_Af1d67709-68fc-4d6a-a644-61ddad078525" dur="minima" oct="4" pname="a"/>
                                <note xml:id="PART05f0e239-2c20-45c2-9e2f-7d2db6cd46ef_Ab95bf9b3-a9a3-431d-94ea-41383f7e84ac" dur="minima" oct="4" pname="a"/>
                                <note xml:id="PART05f0e239-2c20-45c2-9e2f-7d2db6cd46ef_Aef9c83ee-25bf-40d4-843b-42b39d0eb601" dur="minima" oct="4" pname="g"/>
                                <note xml:id="PART05f0e239-2c20-45c2-9e2f-7d2db6cd46ef_Aa6ae890c-c93c-42ce-b1d2-4983b8a6a7a3" dur="semibrevis" oct="4" pname="a"/>
                                <note xml:id="PART05f0e239-2c20-45c2-9e2f-7d2db6cd46ef_A89e463a4-8286-4831-b420-3f5420780c1b" dur="minima" oct="4" pname="g"/>
                                <note xml:id="PART05f0e239-2c20-45c2-9e2f-7d2db6cd46ef_A487b221c-816a-45b8-9d66-9f063d58173d" dur="semibrevis" oct="4" pname="f"/>
                                <barLine form="dashed"/>
                                <note xml:id="PART05f0e239-2c20-45c2-9e2f-7d2db6cd46ef_A59e54c7c-e746-4cbc-b84d-ea5853d7506f" dur="brevis" oct="4" pname="e"/>
                                <barLine form="dashed"/>
                                <rest xml:id="PART05f0e239-2c20-45c2-9e2f-7d2db6cd46ef_Aa5d91e7a-3bd2-4a59-831c-40f99c3f59e4" dur="minima"/>
                                <note xml:id="PART05f0e239-2c20-45c2-9e2f-7d2db6cd46ef_Ae3191b5c-6caa-42ab-80bf-733d999d3a32" dur="minima" oct="4" pname="e"/>
                                <note xml:id="PART05f0e239-2c20-45c2-9e2f-7d2db6cd46ef_A5a4b5379-5c8a-4742-b55f-bdef1347e100" dur="minima" oct="4" pname="e"/>
                                <note xml:id="PART05f0e239-2c20-45c2-9e2f-7d2db6cd46ef_Ad6085094-44b5-49ae-8d05-c73d276f208f" dur="minima" oct="4" pname="d"/>
                                <barLine form="dashed"/>
                                <note xml:id="PART05f0e239-2c20-45c2-9e2f-7d2db6cd46ef_Adf13c5c9-8bca-4b77-920f-e2ae787eb61b" dur="minima" oct="4" pname="e"/>
                                <note xml:id="PART05f0e239-2c20-45c2-9e2f-7d2db6cd46ef_A99f23bae-7bd8-4447-bb0a-9347b2c17713" dur="semibrevis" oct="4" pname="f"/>
                                <note xml:id="PART05f0e239-2c20-45c2-9e2f-7d2db6cd46ef_A346a3e4a-8fa4-413d-a502-f09ca27efb79" dur="minima" oct="4" pname="e"/>
                                <barLine form="dashed"/>
                                <note xml:id="PART05f0e239-2c20-45c2-9e2f-7d2db6cd46ef_Aaeb11214-8c16-4890-8ddb-f21317f85141" dur="minima" oct="4" pname="d"/>
                                <note xml:id="PART05f0e239-2c20-45c2-9e2f-7d2db6cd46ef_A704dcf85-73d6-42bf-9659-d48ebc964a13" dur="semiminima" oct="4" pname="c"/>
                                <note xml:id="PART05f0e239-2c20-45c2-9e2f-7d2db6cd46ef_A55997162-0812-4db3-9c11-6eca764e5151" dur="semiminima" oct="4" pname="d"/>
                                <note xml:id="PART05f0e239-2c20-45c2-9e2f-7d2db6cd46ef_Ad4d37675-2ab4-4817-9446-caaaf8a80a69" dur="semiminima" oct="4" pname="e"/>
                                <note xml:id="PART05f0e239-2c20-45c2-9e2f-7d2db6cd46ef_Ac1ede57f-b62f-4c72-b05a-2139bc7284f3" dur="semiminima" oct="4" pname="f"/>
                                <note xml:id="PART05f0e239-2c20-45c2-9e2f-7d2db6cd46ef_A768dd038-3973-4d0c-8a5c-369e485b0407" dur="semibrevis" oct="4" pname="g">
                                    <verse xml:id="m-e4d40846-9dd5-4ab5-8146-98770435e1c7" color="black" n="1">
                                        <syl xml:id="m-ba917520-120c-4020-8f1a-e2854cb06885" con="b">30r.jpg,</syl>
                                        <syl xml:id="m-8f679601-758e-4482-b007-848372850f2c" con="b">p1,</syl>
                                        <syl xml:id="m-3ec274a4-d5ae-4be9-97c6-e52d41de641c">s3</syl>
                                    </verse>
                                </note>
                                <note xml:id="PART05f0e239-2c20-45c2-9e2f-7d2db6cd46ef_A8db5ace2-ed09-4ad5-881d-3cef9fec3f61" dur="semiminima" oct="4" pname="f"/>
                                <note xml:id="PART05f0e239-2c20-45c2-9e2f-7d2db6cd46ef_Ae65001e3-3179-4b68-8cc8-fedd0fd6c869" dur="semiminima" oct="4" pname="e"/>
                                <note xml:id="PART05f0e239-2c20-45c2-9e2f-7d2db6cd46ef_A55852952-c7dd-422c-8dc2-8c1f00628c51" dur="minima" oct="4" pname="f"/>
                                <note xml:id="PART05f0e239-2c20-45c2-9e2f-7d2db6cd46ef_Aed58e804-4dd8-4a6c-9a0c-bb5eba9029a6" dur="minima" oct="4" pname="e"/>
                                <barLine form="dashed"/>
                                <note xml:id="PART05f0e239-2c20-45c2-9e2f-7d2db6cd46ef_A9434c576-5e3d-4716-b884-1e33e679f891" dur="minima" oct="4" pname="f"/>
                                <note xml:id="PART05f0e239-2c20-45c2-9e2f-7d2db6cd46ef_Aacbbab19-099d-4c5e-9aed-8edb990cc823" dur="minima" oct="4" pname="a"/>
                                <note xml:id="PART05f0e239-2c20-45c2-9e2f-7d2db6cd46ef_Aead815f0-41d7-48f7-bc9a-0ebdac7aafc0" dur="minima" oct="4" pname="a"/>
                                <note xml:id="PART05f0e239-2c20-45c2-9e2f-7d2db6cd46ef_Adb49af36-d0c8-46cd-9f3a-1a625a6e15b0" dur="minima" oct="4" pname="g"/>
                                <barLine form="dashed"/>
                                <note xml:id="PART05f0e239-2c20-45c2-9e2f-7d2db6cd46ef_A1dc52166-116c-4b2e-b266-55728101449d" dur="minima" oct="4" pname="a"/>
                                <note xml:id="PART05f0e239-2c20-45c2-9e2f-7d2db6cd46ef_A66b6665b-ab1d-41e1-a0d9-5bc8733964e6" dur="minima" oct="4" pname="f"/>
                                <note xml:id="PART05f0e239-2c20-45c2-9e2f-7d2db6cd46ef_Aa59d8547-3dd7-4fef-97f2-2d8d7db8485a" dur="semibrevis" oct="4" pname="g"/>
                                <barLine form="dashed"/>
                                <note xml:id="PART05f0e239-2c20-45c2-9e2f-7d2db6cd46ef_Aaed1e266-14b4-414a-8d6b-7d5ca0646d1d" dur="minima" oct="4" pname="f"/>
                                <note xml:id="PART05f0e239-2c20-45c2-9e2f-7d2db6cd46ef_A19b17cb3-e3f8-4717-9d78-428974d33157" dur="minima" oct="4" pname="a" dur.quality="perfecta" num="2" numbase="3"/>
                                <dot xml:id="m-fe917e63-e831-4771-8636-05d9ee0a7834" form="aug"/>
                                <note xml:id="PART05f0e239-2c20-45c2-9e2f-7d2db6cd46ef_A45a0ed6a-2569-4b27-a6e4-abac3a6b46a2" dur="semiminima" oct="4" pname="g"/>
                                <note xml:id="PART05f0e239-2c20-45c2-9e2f-7d2db6cd46ef_A4394f214-b5b9-4a05-ba99-71bd6a4343be" dur="minima" oct="4" pname="g"/>
                                <barLine form="dashed"/>
                                <note xml:id="PART05f0e239-2c20-45c2-9e2f-7d2db6cd46ef_A25095625-ac54-4e9c-bcec-e9ba07ca2796" dur="brevis" oct="4" pname="a"/>
                                <barLine form="dashed"/>
                            </layer>
                        </staff>
                        <staff n="3">
                            <layer n="1">
                                <note xml:id="PARTd1a078fe-4fcd-4ffb-b67d-7409b4d9952b_Abe74b7d0-97d2-48ef-a253-283c2d746afc" dur="semibrevis" oct="3" pname="g">
                                    <verse xml:id="m-892b89a0-3578-48f8-ae85-bdef49399432" color="black" n="1">
                                        <syl xml:id="m-0d522173-9bc2-405c-b69c-bd03da859d53" con="b">29v.jpg,</syl>
                                        <syl xml:id="m-a38c6d10-2ad1-444b-9f19-e7eb3daaa180" con="b">p1,</syl>
                                        <syl xml:id="m-1c65bed3-e8a3-46d7-97a2-67d5ea44a67f">s5</syl>
                                    </verse>
                                </note>
                                <note xml:id="PARTd1a078fe-4fcd-4ffb-b67d-7409b4d9952b_A19cf3d62-0fb2-43be-b354-0f7bce0ecf0a" dur="minima" oct="3" pname="g"/>
                                <note xml:id="PARTd1a078fe-4fcd-4ffb-b67d-7409b4d9952b_A91730ef5-0571-428a-9849-00bb63a92ac2" dur="minima" oct="3" pname="a"/>
                                <barLine form="dashed"/>
                                <note xml:id="PARTd1a078fe-4fcd-4ffb-b67d-7409b4d9952b_Aa9c55cf2-7daa-44f2-aa3c-e172d2b39192" dur="minima" oct="3" pname="b"/>
                                <note xml:id="PARTd1a078fe-4fcd-4ffb-b67d-7409b4d9952b_A638eb714-5e66-4928-8e15-05db8ae376c7" dur="minima" oct="4" pname="c"/>
                                <note xml:id="PARTd1a078fe-4fcd-4ffb-b67d-7409b4d9952b_A5a7978de-4251-44d0-a257-15b5cc34633f" dur="semibrevis" oct="4" pname="d"/>
                                <barLine form="dashed"/>
                                <note xml:id="PARTd1a078fe-4fcd-4ffb-b67d-7409b4d9952b_Acecd563e-8917-4d8a-bb73-14d18e287deb" dur="semibrevis" oct="4" pname="e" dur.quality="perfecta" num="2" numbase="3"/>
                                <dot xml:id="m-50febf63-8211-4793-b035-c28fc4d2fb62" form="aug"/>
                                <note xml:id="PARTd1a078fe-4fcd-4ffb-b67d-7409b4d9952b_Ac1a34f9f-6274-4baf-a39f-3794d8966c33" dur="semiminima" oct="4" pname="d"/>
                                <note xml:id="PARTd1a078fe-4fcd-4ffb-b67d-7409b4d9952b_A19ff29fe-84c8-4947-b961-b382eb6bd3a7" dur="semiminima" oct="4" pname="c"/>
                                <barLine form="dashed"/>
                                <note xml:id="PARTd1a078fe-4fcd-4ffb-b67d-7409b4d9952b_Ab676ab2f-12ca-4ebd-b015-898d7ff56aa8" dur="minima" oct="4" pname="d"/>
                                <note xml:id="PARTd1a078fe-4fcd-4ffb-b67d-7409b4d9952b_A532fb351-b050-49dd-8ff7-b1c2de57de22" dur="minima" oct="4" pname="e"/>
                                <note xml:id="PARTd1a078fe-4fcd-4ffb-b67d-7409b4d9952b_A8a82ae26-3ade-43d3-b34f-8ecdf3107876" dur="minima" oct="4" pname="f"/>
                                <note xml:id="PARTd1a078fe-4fcd-4ffb-b67d-7409b4d9952b_A418d677d-81b4-41fc-bc92-763e4c7dbc0a" dur="minima" oct="4" pname="g" dur.quality="perfecta" num="2" numbase="3"/>
                                <dot xml:id="m-190b0ba2-4b6f-41ba-8c45-73c59664d0fc" form="aug"/>
                                <note xml:id="PARTd1a078fe-4fcd-4ffb-b67d-7409b4d9952b_A1a2db0a4-6a84-4ac2-a655-4fa720515f62" dur="semiminima" oct="4" pname="f"/>
                                <note xml:id="PARTd1a078fe-4fcd-4ffb-b67d-7409b4d9952b_A0b8947d8-e655-45a0-a290-482289fa2731" dur="semiminima" oct="4" pname="e">
                                    <verse xml:id="m-b7995ec1-dcf3-4804-a0f6-e59fde6a9416" color="black" n="1">
                                        <syl xml:id="m-9d01cb1d-ddaa-4c0a-9cb1-ecdbc35b0734" con="b">29v.jpg,</syl>
                                        <syl xml:id="m-4e7b17fd-0018-4ac3-803c-1914242f19cf" con="b">p1,</syl>
                                        <syl xml:id="m-08442b8d-54b7-4f00-85b9-c3ee5c15d664">s6</syl>
                                    </verse>
                                </note>
                                <note xml:id="PARTd1a078fe-4fcd-4ffb-b67d-7409b4d9952b_A80699c9b-105c-484a-bb1d-e18ec3e9d1a3" dur="semiminima" oct="4" pname="d"/>
                                <note xml:id="PARTd1a078fe-4fcd-4ffb-b67d-7409b4d9952b_Aafaea57f-2eed-443b-a4b9-c2559b018714" dur="minima" oct="4" pname="e"/>
                                <note xml:id="PARTd1a078fe-4fcd-4ffb-b67d-7409b4d9952b_A62cab5d7-51aa-4976-8943-1f5b3a87c8ba" dur="minima" oct="4" pname="d"/>
                                <barLine form="dashed"/>
                                <note xml:id="PARTd1a078fe-4fcd-4ffb-b67d-7409b4d9952b_A12184e79-7e24-4b4e-ab1a-f0d4be0c0c7f" dur="minima" oct="4" pname="c"/>
                                <note xml:id="PARTd1a078fe-4fcd-4ffb-b67d-7409b4d9952b_A8d5324d4-891e-4581-b73e-4f35ae2ce449" dur="minima" oct="4" pname="d"/>
                                <note xml:id="PARTd1a078fe-4fcd-4ffb-b67d-7409b4d9952b_Aa1dcce98-7511-4346-a75c-7b7b3a0c6647" dur="semibrevis" oct="3" pname="b"/>
                                <barLine form="dashed"/>
                                <note xml:id="PARTd1a078fe-4fcd-4ffb-b67d-7409b4d9952b_A995c3bd0-0678-4b12-beda-676ecda7eee8" dur="brevis" oct="3" pname="a"/>
                                <barLine form="dashed"/>
                                <choice>
                                    <corr>
                                        <rest xml:id="m-abb18e61-4820-4fec-89e0-796fa5534d6d" dur="brevis"/>
                                    </corr>
                                    <sic>
                                        <rest xml:id="PARTd1a078fe-4fcd-4ffb-b67d-7409b4d9952b_Afdc42598-5a75-4d6b-982e-e566186a64a2" dur="semibrevis"/>
                                    </sic>
                                </choice>
                                <barLine form="dashed"/>
                                <rest xml:id="PARTd1a078fe-4fcd-4ffb-b67d-7409b4d9952b_Ac2f7ae41-f106-42cc-b0b8-86b8981f0425" dur="minima"/>
                                <note xml:id="PARTd1a078fe-4fcd-4ffb-b67d-7409b4d9952b_Ac1a27c32-6b40-4456-aa07-fca5cdc28fb3" dur="minima" oct="4" pname="e"/>
                                <note xml:id="PARTd1a078fe-4fcd-4ffb-b67d-7409b4d9952b_A050718a5-bf4a-4f87-8932-b144323d90bf" dur="minima" oct="4" pname="e"/>
                                <note xml:id="PARTd1a078fe-4fcd-4ffb-b67d-7409b4d9952b_A813efed7-65a6-437a-8842-eb7d9a1ae778" dur="minima" oct="4" pname="e"/>
                                <barLine form="dashed"/>
                                <note xml:id="PARTd1a078fe-4fcd-4ffb-b67d-7409b4d9952b_A4db7a5e6-4276-44ad-8a34-0839c7f784cf" dur="minima" oct="3" pname="a"/>
                                <note xml:id="PARTd1a078fe-4fcd-4ffb-b67d-7409b4d9952b_Ac7c6f67b-2002-459a-bcf4-e036c0f6d1ba" dur="semibrevis" oct="4" pname="d"/>
                                <note xml:id="PARTd1a078fe-4fcd-4ffb-b67d-7409b4d9952b_A19c9b383-42bd-4991-ae62-461dec03680d" dur="semiminima" oct="4" pname="c"/>
                                <note xml:id="PARTd1a078fe-4fcd-4ffb-b67d-7409b4d9952b_A8226499e-e843-4a6c-aca9-6b78321977b2" dur="semiminima" oct="3" pname="b"/>
                                <barLine form="dashed"/>
                                <note xml:id="PARTd1a078fe-4fcd-4ffb-b67d-7409b4d9952b_Abc8d67ac-179b-42cf-85ec-b5c6ff3e8643" dur="minima" oct="4" pname="c"/>
                                <note xml:id="PARTd1a078fe-4fcd-4ffb-b67d-7409b4d9952b_A849fea0d-702e-4c5b-831c-ecbf42e5e087" dur="minima" oct="4" pname="d"/>
                                <note xml:id="PARTd1a078fe-4fcd-4ffb-b67d-7409b4d9952b_Afbfdc194-4733-45f3-b122-6021d159798b" dur="minima" oct="4" pname="e">
                                    <verse xml:id="m-64cc97e6-deb5-40d5-98d6-75e3b2c751af" color="black" n="1">
                                        <syl xml:id="m-ce1abf06-78ef-4b5c-a3bc-40fb149c30b0" con="b">29v.jpg,</syl>
                                        <syl xml:id="m-a845ce6b-3698-4638-b1b2-b9f25c2803af" con="b">p1,</syl>
                                        <syl xml:id="m-dcb8044d-b60b-418f-952f-b68879fa19d9">s7</syl>
                                    </verse>
                                </note>
                                <note xml:id="PARTd1a078fe-4fcd-4ffb-b67d-7409b4d9952b_A127e0e2a-9cf3-460f-8562-7fa50c972a42" dur="semibrevis" oct="4" pname="f"/>
                                <note xml:id="PARTd1a078fe-4fcd-4ffb-b67d-7409b4d9952b_A02039d68-f765-4831-ac82-4efd7605f1ad" dur="minima" oct="4" pname="c"/>
                                <note xml:id="PARTd1a078fe-4fcd-4ffb-b67d-7409b4d9952b_A6393fcec-f7eb-4c8b-82ae-f99b4e304f64" dur="semibrevis" oct="4" pname="d"/>
                                <barLine form="dashed"/>
                                <rest xml:id="PARTd1a078fe-4fcd-4ffb-b67d-7409b4d9952b_A6a6ea701-ff84-4bad-aa38-2b04268e39ed" dur="minima"/>
                                <note xml:id="PARTd1a078fe-4fcd-4ffb-b67d-7409b4d9952b_Ac246711d-937f-42b2-8699-8c771f781725" dur="minima" oct="3" pname="a"/>
                                <note xml:id="PARTd1a078fe-4fcd-4ffb-b67d-7409b4d9952b_Af2136e1f-fb95-42ab-be20-65da1efe32e5" dur="minima" oct="3" pname="a"/>
                                <note xml:id="PARTd1a078fe-4fcd-4ffb-b67d-7409b4d9952b_A5cf5b2fa-986b-4b9d-b638-bc97bad7d239" dur="minima" oct="3" pname="g"/>
                                <barLine form="dashed"/>
                                <note xml:id="PARTd1a078fe-4fcd-4ffb-b67d-7409b4d9952b_Afbffa762-7a41-4d51-bede-d272804b6537" dur="minima" oct="3" pname="a"/>
                                <note xml:id="PARTd1a078fe-4fcd-4ffb-b67d-7409b4d9952b_Af1786814-8e58-4836-9136-e5fddd6f2195" dur="semibrevis" oct="4" pname="c"/>
                                <note xml:id="PARTd1a078fe-4fcd-4ffb-b67d-7409b4d9952b_A5d5eb05e-170b-471c-beb2-7a948761cc9e" dur="minima" oct="3" pname="b"/>
                                <barLine form="dashed"/>
                                <note xml:id="PARTd1a078fe-4fcd-4ffb-b67d-7409b4d9952b_A494222ec-7fdb-4e8d-be32-b9164879a565" dur="semibrevis" oct="3" pname="a"/>
                                <rest xml:id="PARTd1a078fe-4fcd-4ffb-b67d-7409b4d9952b_Ac5dd3156-c700-4ab2-9c60-bb0f6b3374b1" dur="semibrevis"/>
                                <barLine form="dashed"/>
                                <rest xml:id="PARTd1a078fe-4fcd-4ffb-b67d-7409b4d9952b_A71eff7dc-928b-4fbe-a816-9b9c79f16a9b" dur="minima"/>
                                <note xml:id="PARTd1a078fe-4fcd-4ffb-b67d-7409b4d9952b_A5087d597-d1f7-414f-b84f-f53e9127684f" dur="minima" oct="3" pname="a"/>
                                <note xml:id="PARTd1a078fe-4fcd-4ffb-b67d-7409b4d9952b_A4b87d27a-d30d-415b-b2e7-663541520e34" dur="minima" oct="3" pname="a"/>
                                <note xml:id="PARTd1a078fe-4fcd-4ffb-b67d-7409b4d9952b_A7d25d81a-bac7-4274-8ce2-d880ee30db97" dur="minima" oct="3" pname="g"/>
                                <barLine form="dashed"/>
                                <note xml:id="PARTd1a078fe-4fcd-4ffb-b67d-7409b4d9952b_A5c6484c0-48bc-44ee-8ed2-17f980a6d03a" dur="minima" oct="3" pname="a"/>
                                <note xml:id="PARTd1a078fe-4fcd-4ffb-b67d-7409b4d9952b_Ae3d57844-f1a6-4464-b5a0-9bb4dc2fe6ca" dur="minima" oct="4" pname="d"/>
                                <note xml:id="PARTd1a078fe-4fcd-4ffb-b67d-7409b4d9952b_A9255fed8-0edf-4b54-87f5-8cce3cc3d447" dur="minima" oct="4" pname="d"/>
                                <note xml:id="PARTd1a078fe-4fcd-4ffb-b67d-7409b4d9952b_A8b22181f-988a-4414-9887-2fb37da10309" dur="minima" oct="4" pname="c">
                                    <verse xml:id="m-febad1cc-3f2c-4cd8-86e9-d7696e9c18ab" color="black" n="1">
                                        <syl xml:id="m-32b168c7-a006-41cd-9c80-16b21a7b37f0" con="b">29v.jpg,</syl>
                                        <syl xml:id="m-b739386c-e0e6-4c1f-9dc5-33df4d686d9e" con="b">p1,</syl>
                                        <syl xml:id="m-8c55d1fc-3bd1-40ba-8e14-a26a0f6b5a98">s8</syl>
                                    </verse>
                                </note>
                                <barLine form="dashed"/>
                                <note xml:id="PARTd1a078fe-4fcd-4ffb-b67d-7409b4d9952b_A24ff9742-7e52-429e-bf85-42b1d403f47a" dur="minima" oct="4" pname="d"/>
                                <note xml:id="PARTd1a078fe-4fcd-4ffb-b67d-7409b4d9952b_Aa8024a5b-aedb-4cda-b6b3-c337ce0b3495" dur="semibrevis" oct="4" pname="f"/>
                                <note xml:id="PARTd1a078fe-4fcd-4ffb-b67d-7409b4d9952b_A43e91ec8-8928-443f-be01-7bd3d6004e2c" dur="minima" oct="4" pname="e"/>
                                <barLine form="dashed"/>
                                <note xml:id="PARTd1a078fe-4fcd-4ffb-b67d-7409b4d9952b_A96c1595d-2142-4643-bff2-3ab69f452db2" dur="semibrevis" oct="4" pname="d"/>
                                <note xml:id="PARTd1a078fe-4fcd-4ffb-b67d-7409b4d9952b_A83ab036d-1f9a-4868-9e41-dcb83b5eff4d" dur="semibrevis" oct="4" pname="c"/>
                                <barLine form="dashed"/>
                                <note xml:id="PARTd1a078fe-4fcd-4ffb-b67d-7409b4d9952b_A9ae72cb1-81d0-427d-8e19-901e6130daaa" dur="semibrevis" oct="4" pname="d"/>
                                <note xml:id="PARTd1a078fe-4fcd-4ffb-b67d-7409b4d9952b_A883af986-752f-42ad-b1c7-c09764764698" dur="semibrevis" oct="3" pname="b"/>
                                <barLine form="dashed"/>
                                <note xml:id="PARTd1a078fe-4fcd-4ffb-b67d-7409b4d9952b_Ad5c12d51-1885-467f-aac7-fdb1458b6e0d" dur="brevis" oct="3" pname="a"/>
                                <barLine form="dashed"/>
                            </layer>
                        </staff>
                    </section>
                </score>
            </mdiv>
        </body>
    </music>
</mei>